{
  "name": "NotBDArmory",
  "description": "A mod that strives to add new weapons to VTOL VR. Special thanks to Mallikas, Notboris, and Malx for the models!",
  "dll_file": "NotBDArmory.dll",
  "last_edit": 637633728151806057,
  "pub_id": "",
  "json_version": "",
  "version": "1.0.0",
  "tagline": "Better than BahamutoD this time.",
  "repository": "",
  "is_public": true,
  "unlisted": false,
  "preview_image": "",
  "web_preview_image": "preview.png",
  "dependencies": [],
  "mod_dependencies": null,
  "ContentType": 0
}